ntsim/Events2Hits.py
ntsim/__about__.py
ntsim/__init__.py
ntsim/__main__.py
ntsim/random.py
ntsim/Analysis/BGVDTestAnalysis.py
ntsim/Analysis/EffectiveVolume.py
ntsim/Analysis/SaveHitSum.py
ntsim/Analysis/SaveHitSumWithTime.py
ntsim/Analysis/TriggerAnalysis.py
ntsim/Analysis/__init__.py
ntsim/Analysis/Base/AnalysisBase.py
ntsim/Analysis/Factory/AnalysisFactory.py
ntsim/Base/BaseConfig.py
ntsim/Base/BaseFactory.py
ntsim/Base/RunConfiguration.py
ntsim/Base/__init__.py
ntsim/BoundingSurfaces/BoundingBox.py
ntsim/BoundingSurfaces/BoundingCylinder.py
ntsim/BoundingSurfaces/BoundingSphere.py
ntsim/BoundingSurfaces/__init__.py
ntsim/BoundingSurfaces/Base/BoundingBase.py
ntsim/CherenkovGenerators/CherenkovGenerator.py
ntsim/CherenkovGenerators/__init__.py
ntsim/CherenkovGenerators/cher_utils.py
ntsim/CherenkovGenerators/Base/CherenkovBase.py
ntsim/CherenkovGenerators/Factory/CherenkovGeneratorFactory.py
ntsim/CloneGenerators/CloneGenerator.py
ntsim/CloneGenerators/Base/CloneBase.py
ntsim/CloneGenerators/Factory/CloneGeneratorFactory.py
ntsim/IO/H5Writer.py
ntsim/IO/__init__.py
ntsim/IO/gEvent.py
ntsim/IO/gHits.py
ntsim/IO/gParticles.py
ntsim/IO/gPhotons.py
ntsim/IO/gTracks.py
ntsim/IO/h5Reader.py
ntsim/IO/Base/StructData.py
ntsim/IO/Base/WriterBase.py
ntsim/IO/Factories/WriterFactory.py
ntsim/IO/converters/g4data.py
ntsim/MediumProperties/BaikalWaterProperties.py
ntsim/MediumProperties/Example1MediumProperties.py
ntsim/MediumProperties/Base/BaseMediumProperties.py
ntsim/MediumProperties/Factory/MediumPropertiesFactory.py
ntsim/MediumScatteringModels/Flat.py
ntsim/MediumScatteringModels/HGplusRayleigh.py
ntsim/MediumScatteringModels/HenyeyGreenstein.py
ntsim/MediumScatteringModels/Rayleigh.py
ntsim/MediumScatteringModels/Base/MediumScatteringModelBase.py
ntsim/MediumScatteringModels/Factory/MediumScatteringModelsFactory.py
ntsim/PrimaryGenerators/CorsikaBundlesGenerator.py
ntsim/PrimaryGenerators/CorsikaGVDDataBankReader.py
ntsim/PrimaryGenerators/Diffuser.py
ntsim-0.2.0.dist-info/METADATA
ntsim-0.2.0.dist-info/WHEEL
ntsim-0.2.0.dist-info/licenses/LICENSE.txt
ntsim-0.2.0.dist-info/RECORD
