Metadata-Version: 2.4
Name: ntsim
Version: 0.2.0
Summary: Neutrino Telescope Simulation
Project-URL: Documentation, https://git.jinr.ru/Baikal/ntsim#readme
Project-URL: Issues, https://git.jinr.ru/Baikal/ntsim/issues
Project-URL: Source, https://git.jinr.ru/Baikal/ntsim
Author: Sergey Zavyalov, Andrey Sheshukov, Daniil Zubchenko, Mikhail Lisitsin, Yuri Malyshkin
Author-email: Dmitry Naumov <dmitryvnaumov@gmail.com>
License-Expression: MIT
License-File: LICENSE.txt
Classifier: Development Status :: 4 - Beta
Classifier: Programming Language :: Python
Classifier: Programming Language :: Python :: 3.10
Classifier: Programming Language :: Python :: 3.11
Classifier: Programming Language :: Python :: 3.12
Classifier: Programming Language :: Python :: 3.13
Classifier: Programming Language :: Python :: Implementation :: CPython
Classifier: Programming Language :: Python :: Implementation :: PyPy
Requires-Python: >=3.10
Requires-Dist: configargparse
Requires-Dist: g4camp>=0.1.23
Requires-Dist: h5py
Requires-Dist: numba
Requires-Dist: numpy
Requires-Dist: pandas
Requires-Dist: particle
Requires-Dist: pyyaml
Requires-Dist: scipy
Requires-Dist: tqdm
Provides-Extra: base
Provides-Extra: extra
Requires-Dist: icosphere; extra == 'extra'
Requires-Dist: pvlib; extra == 'extra'
Requires-Dist: vector; extra == 'extra'
Provides-Extra: gui
Requires-Dist: matplotlib; extra == 'gui'
Requires-Dist: pyopengl; extra == 'gui'
Requires-Dist: pyqt5; extra == 'gui'
Requires-Dist: pyqtgraph; extra == 'gui'
Requires-Dist: webcolors; extra == 'gui'
Provides-Extra: nupropagator
Requires-Dist: nupropagator>=0.0.2; extra == 'nupropagator'
Provides-Extra: test
Requires-Dist: pytest; extra == 'test'
